fvdb_reality_capture/__init__.py
fvdb_reality_capture/cli/__init__.py
fvdb_reality_capture/cli/frdev/__init__.py
fvdb_reality_capture/cli/frdev/_s3.py
fvdb_reality_capture/cli/frgs/__init__.py
fvdb_reality_capture/cli/frgs/_common.py
fvdb_reality_capture/cli/frgs/_convert.py
fvdb_reality_capture/cli/frgs/_download.py
fvdb_reality_capture/cli/frgs/_evaluate.py
fvdb_reality_capture/cli/frgs/_mesh_basic.py
fvdb_reality_capture/cli/frgs/_mesh_dlnr.py
fvdb_reality_capture/cli/frgs/_points.py
fvdb_reality_capture/cli/frgs/_reconstruct.py
fvdb_reality_capture/cli/frgs/_resume.py
fvdb_reality_capture/cli/frgs/_show.py
fvdb_reality_capture/cli/frgs/_show_data.py
fvdb_reality_capture/dev/__init__.py
fvdb_reality_capture/dev/s3.py
fvdb_reality_capture/foundation_models/__init__.py
fvdb_reality_capture/foundation_models/config.py
fvdb_reality_capture/foundation_models/dlnr.py
fvdb_reality_capture/foundation_models/sam2.py
fvdb_reality_capture/radiance_fields/__init__.py
fvdb_reality_capture/radiance_fields/base_gaussian_splat_optimizer.py
fvdb_reality_capture/radiance_fields/camera_pose_adjust.py
fvdb_reality_capture/radiance_fields/gaussian_splat_dataset.py
fvdb_reality_capture/radiance_fields/gaussian_splat_optimizer.py
fvdb_reality_capture/radiance_fields/gaussian_splat_reconstruction.py
fvdb_reality_capture/radiance_fields/gaussian_splat_reconstruction_writer.py
fvdb_reality_capture/radiance_fields/_private/__init__.py
fvdb_reality_capture/radiance_fields/_private/appearance_adjust.py
fvdb_reality_capture/radiance_fields/_private/lpips.py
fvdb_reality_capture/radiance_fields/_private/utils.py
fvdb_reality_capture/sfm_scene/__init__.py
fvdb_reality_capture/sfm_scene/_load_colmap_scene.py
fvdb_reality_capture/sfm_scene/_load_e57_scene.py
fvdb_reality_capture/sfm_scene/_load_simple_scene.py
fvdb_reality_capture/sfm_scene/sfm_cache.py
fvdb_reality_capture/sfm_scene/sfm_metadata.py
fvdb_reality_capture/sfm_scene/sfm_scene.py
fvdb_reality_capture-0.3.0.dist-info/licenses/LICENSE
fvdb_reality_capture-0.3.0.dist-info/METADATA
fvdb_reality_capture-0.3.0.dist-info/WHEEL
fvdb_reality_capture-0.3.0.dist-info/entry_points.txt
fvdb_reality_capture-0.3.0.dist-info/top_level.txt
fvdb_reality_capture-0.3.0.dist-info/RECORD
